{
  "rodovia": "PR-151",
  "itens": [
    {
      "id": "d0",
      "tramo": "15",
      "kmIni": "404+267",
      "kmFim": "404+132",
      "latI": "-25.587714",
      "lonI": "-50.159401",
      "latF": "-25.586543",
      "lonF": "-50.159473",
      "eixo": "PR-151",
      "lado": "LE",
      "comprimento": "132",
      "modelo": "H1 A W4",
      "termEntrada": "ABSORVEDOR DE ENERGIA",
      "termSaida": "ABSORVEDOR DE ENERGIA",
      "velocidade": "80",
      "funcao": "TALUDE"
    },
    {
      "id": "d1",
      "tramo": "25",
      "kmIni": "420+142",
      "kmFim": "420+285",
      "latI": "-25.663797",
      "lonI": "-50.270368",
      "latF": "-25.664476",
      "lonF": "-50.271589",
      "eixo": "PR-151",
      "lado": "LD",
      "comprimento": "144",
      "modelo": "H1 A W4",
      "termEntrada": "ABSORVEDOR DE ENERGIA",
      "termSaida": "ABSORVEDOR DE ENERGIA",
      "velocidade": "80",
      "funcao": "TALUDE"
    },
    {
      "id": "d2",
      "tramo": "34",
      "kmIni": "424+908",
      "kmFim": "425+031",
      "latI": "-25.681883",
      "lonI": "-50.310455",
      "latF": "-25.681959",
      "lonF": "-50.311687",
      "eixo": "PR-151",
      "lado": "LD",
      "comprimento": "124",
      "modelo": "H1 A W4",
      "termEntrada": "ABSORVEDOR DE ENERGIA",
      "termSaida": "ABSORVEDOR DE ENERGIA",
      "velocidade": "80",
      "funcao": "TALUDE"
    },
    {
      "id": "d3",
      "tramo": "35",
      "kmIni": "425+439",
      "kmFim": "425+662",
      "latI": "-25.682361",
      "lonI": "-50.315728",
      "latF": "-25.682865",
      "lonF": "-50.317877",
      "eixo": "PR-151",
      "lado": "LD",
      "comprimento": "224",
      "modelo": "H1 A W4",
      "termEntrada": "ABSORVEDOR DE ENERGIA",
      "termSaida": "ABSORVEDOR DE ENERGIA",
      "velocidade": "80",
      "funcao": "TALUDE"
    },
    {
      "id": "d4",
      "tramo": "45",
      "kmIni": "439+525",
      "kmFim": "439+553",
      "latI": "-25.777328",
      "lonI": "-50.33969",
      "latF": "-25.777593",
      "lonF": "-50.339726",
      "eixo": "PR-151",
      "lado": "LD",
      "comprimento": "28",
      "modelo": "H1 A W4",
      "termEntrada": "ABSORVEDOR DE ENERGIA",
      "termSaida": "ABSORVEDOR DE ENERGIA",
      "velocidade": "60",
      "funcao": "TALUDE"
    },
    {
      "id": "d5",
      "tramo": "46",
      "kmIni": "439+553",
      "kmFim": "439+525",
      "latI": "-25.777556",
      "lonI": "-50.339811",
      "latF": "-25.777366",
      "lonF": "-50.339604",
      "eixo": "PR-151",
      "lado": "LE",
      "comprimento": "28",
      "modelo": "H1 A W4",
      "termEntrada": "ABSORVEDOR DE ENERGIA",
      "termSaida": "ABSORVEDOR DE ENERGIA",
      "velocidade": "60",
      "funcao": "TALUDE"
    },
    {
      "id": "d6",
      "tramo": "47",
      "kmIni": "439+967",
      "kmFim": "440+039",
      "latI": "-25.781202",
      "lonI": "-50.3395",
      "latF": "-25.781851",
      "lonF": "-50.339452",
      "eixo": "PR-151",
      "lado": "LE",
      "comprimento": "72",
      "modelo": "H1 A W4",
      "termEntrada": "ABSORVEDOR DE ENERGIA",
      "termSaida": "ABSORVEDOR DE ENERGIA",
      "velocidade": "60",
      "funcao": "OBSTÁCULO FIXO"
    },
    {
      "id": "d7",
      "tramo": "50",
      "kmIni": "444+394",
      "kmFim": "444+519",
      "latI": "-25.81931",
      "lonI": "-50.341313",
      "latF": "-25.820243",
      "lonF": "-50.341983",
      "eixo": "PR-151",
      "lado": "LD",
      "comprimento": "124",
      "modelo": "H1 A W4",
      "termEntrada": "ABSORVEDOR DE ENERGIA",
      "termSaida": "ABSORVEDOR DE ENERGIA",
      "velocidade": "80",
      "funcao": "TALUDE"
    },
    {
      "id": "d8",
      "tramo": "51",
      "kmIni": "444+520",
      "kmFim": "444+481",
      "latI": "-25.82031",
      "lonI": "-50.341924",
      "latF": "-25.820038",
      "lonF": "-50.341661",
      "eixo": "PR-151",
      "lado": "LE",
      "comprimento": "40",
      "modelo": "H1 A W4",
      "termEntrada": "ABSORVEDOR DE ENERGIA",
      "termSaida": "ABSORVEDOR DE ENERGIA",
      "velocidade": "80",
      "funcao": "TALUDE"
    },
    {
      "id": "d9",
      "tramo": "68",
      "kmIni": "471+811",
      "kmFim": "471+846",
      "latI": "-26.010432",
      "lonI": "-50.358208",
      "latF": "-26.010684",
      "lonF": "-50.357982",
      "eixo": "PR-151",
      "lado": "LD",
      "comprimento": "36",
      "modelo": "H1 A W4",
      "termEntrada": "ABSORVEDOR DE ENERGIA",
      "termSaida": "ABSORVEDOR DE ENERGIA",
      "velocidade": "80",
      "funcao": "TALUDE"
    },
    {
      "id": "d10",
      "tramo": "11",
      "kmIni": "384+036",
      "kmFim": "383+926",
      "latI": "-25.475839",
      "lonI": "-50.031285",
      "latF": "-25.475097",
      "lonF": "-50.030553",
      "eixo": "PR-151",
      "lado": "LE",
      "comprimento": "20",
      "modelo": "H1 A W4",
      "termEntrada": "ABSORVEDOR DE ENERGIA",
      "termSaida": "EM CONDIÇÃO DE USO",
      "velocidade": "60",
      "funcao": "TALUDE"
    },
    {
      "id": "d11",
      "tramo": "14",
      "kmIni": "390+624",
      "kmFim": "390+782",
      "latI": "-25.502698",
      "lonI": "-50.085505",
      "latF": "-25.503713",
      "lonF": "-50.086609",
      "eixo": "PR-151",
      "lado": "LD",
      "comprimento": "0",
      "modelo": "H1 A W4",
      "termEntrada": "ABSORVEDOR DE ENERGIA",
      "termSaida": "EM CONDIÇÃO DE USO",
      "velocidade": "60",
      "funcao": "TALUDE"
    },
    {
      "id": "d12",
      "tramo": "16",
      "kmIni": "405+295",
      "kmFim": "405+031",
      "latI": "-25.594319",
      "lonI": "-50.160822",
      "latF": "-25.593921",
      "lonF": "-50.158289",
      "eixo": "PR-151",
      "lado": "LE",
      "comprimento": "90",
      "modelo": "H1 A W4",
      "termEntrada": "EM CONDIÇÃO DE USO",
      "termSaida": "EM CONDIÇÃO DE USO",
      "velocidade": "80",
      "funcao": "TALUDE"
    }
  ]
}